datacustodian/__init__.py
datacustodian/api.py
datacustodian/base.py
datacustodian/crypto.py
datacustodian/datacustodian_app.py
datacustodian/db.py
datacustodian/dlt.py
datacustodian/io.py
datacustodian/ipfs.py
datacustodian/msg.py
datacustodian/settings.py
datacustodian/testing.py
datacustodian/utility.py
datacustodian/writers.py
datacustodian/agent/__init__.py
datacustodian/agent/connections.py
datacustodian/agent/credentials.py
datacustodian/agent/definitions.py
datacustodian/agent/handlers.py
datacustodian/agent/ledger.py
datacustodian/agent/menu.py
datacustodian/agent/presentation.py
datacustodian/agent/server.py
datacustodian/agent/wallet.py
datacustodian/consent/__init__.py
datacustodian/consent/auth.py
datacustodian/consent/circles.py
datacustodian/consent/files.py
datacustodian/consent/offers.py
datacustodian/consent/sharing.py
datacustodian/identity/__init__.py
datacustodian/identity/did.py
datacustodian/identity/fido.py
datacustodian/templates/_conftest.py
datacustodian/templates/browser.html
datacustodian/templates/client_component.py
datacustodian/templates/client_init.py
datacustodian/templates/component.py
datacustodian/templates/conftest.py
datacustodian/templates/init.py
datacustodian/templates/logging.conf
datacustodian/templates/setup.py
datacustodian/templates/t_component.py
datacustodian/templates/test_component.py
datacustodian/templates/wsgi.py
datacustodian-1.2.1.data/scripts/datacustodian_app.py
datacustodian-1.2.1.dist-info/LICENSE
datacustodian-1.2.1.dist-info/METADATA
datacustodian-1.2.1.dist-info/WHEEL
datacustodian-1.2.1.dist-info/top_level.txt
datacustodian-1.2.1.dist-info/RECORD
